{"url": "http://news.naver.com/main/read.nhn?mode=LSD&mid=shm&sid1=100&oid=081&aid=0002811221", "datetime": "2017-04-05 13:47", "contents": "[서울신문]안철수, 기자들과 간담회 - 국민의당 안철수 대선후보가 5일 오전 국회에서 기자간담회를 열고 있다. 2017.4.5 연합뉴스안철수 국민의당 대선후보가 5일 문재인 더불어민주당 대선후보에 양자 끝장토론을 제안했다.안 후보는 이날 국회에서 열린 기자회견에서 “국민이 짧은 30여 일 동안 누가 제대로 준비된 사람인지 판단할 수 있도록 더불어민주당 문재인 후보와의 양자 끝장토론을 제안한다”고 말했다.그는 “문 후보 스스로가 이번에는 대선후보 검증이 중요하니까 끝장토론이 필요하다고 말씀하신 적이 있다”며 이같이 제안했다.안 후보는 회견에서 “저는 누구를 반대하기 위해 나온 게 아니다. 제가 가진 비전과 리더십이 더 낫기 때문에 나온 것”이라며 “대선 구도는 안철수와 문재인 두 사람 중 누구에 의한 정권교체가 나은 것인가다. 남은 부분이 인물과 정책으로, 저는 자신 있다는 말씀을 드리고 싶다”고 강조했다.그는 “끝장 양자토론도 꼭 필요하고 다자토론도 물론 필요하다”며 “이번에는 요청이 들어오는 모든 곳에 가능한 한 토론이 진행돼야 한다”고 했다.안 후보는 “박근혜 전 대통령을 뽑고 나서 폐해를 많이 깨닫고 있지 않으냐”라며 “본인이 가진 생각이 아니라 전문가들이 만들어준 정책과 내용을 갖고 외우거나 읽거나 하면서 미처 검증이 안 돼 당선된 것이다”라고 지적했다.이어 “그러다 보니 대통령에 당선된 이후에는 자기 생각이 아니니 다 잊어버리고 원래 자기가 생각한 우선순위와 가치관대로 국정을 운영해왔던 것이다. 이제는 그런 일이 있으면 안 된다”고 했다.안 후보는 “준비된 종이서류 없이 미국 토론처럼 맨몸으로 자유롭게 끝장토론을 하게 되면 실제로 가지고 있는 생각이 어떤 것인지 알 수 있을 것”이라고 강조했다.김서연 기자 wk@seoul.co.kr▶  재미있는 세상[나우뉴스], [웰 메이드 N] ▶ [인기 무료만화] [페이스북]ⓒ 서울신문(www.seoul.co.kr), 무단전재 및 재배포금지", "press": "서울신문", "title": "안철수 “문재인 후보와의 양자 끝장토론 제안”"}