{"url": "http://news.naver.com/main/read.nhn?mode=LSD&mid=shm&sid1=100&oid=029&aid=0002394524", "title": "안철수 호남 돌풍.. 반문 전선 선봉으로 나설까+안철수 부산 공략 본격화", "press": "디지털타임스", "datetime": "2017-03-27 17:04", "contents": "안철수 전 국민의당 대표가 일으키는 '호남 돌풍'이 심상치 않다. 안 전 대표는 국민의당은 물론 더불어민주당의 '텃밭'인 호남 경선에서 손학규 전 민주당 대표, 박주선 국회부의장과 붙어, 압도적인 승리를 거뒀다. 안 전 대표는 지난 25일 광주·전남·제주에서 치러진 국민의당 첫 순회경선에서 60.69%를 얻어 압도적인 1위를 기록했다.안 전 대표가 호남에서 압승을 거둔 것은 많은 의미를 내포한다. 당초 안 전 대표는 '지지율 10%'대의 대권 주자에 불과하다는 회의적 시각을 받아왔다. 하지만 국민의당 최대 승부처인 호남권에서 안 전 대표는 60%가 넘는 지지를 얻었다. 이는 안 전 대표가 국민의당 대선 후보로서 '본선 경쟁력'을 확보했다는 의미가 된다. 특히 역시 호남권을 '텃밭'으로 삼고 있는 더불어민주당의 대표를 지낸 문재인 전 대표의 대항마로서 존재감을 크게 부각시켰다는 분석도 나오고 있다. 안 전 대표의 '본선 경쟁력', 문 전 대표에 대한 '대항마'라는 이미지를 합산하면 문 전 대표에 대한 호남권의 '반 문재인' 정서가 입증됐다는 분석도 있다. 안 전 대표는 호남권 승리로 손 전 대표, 박 부의장에 비해 국민의당 대선 후보 경선에서 유리한 고지를 선점했다. 안 전 대표는 이날 호남권 승리를 바탕으로 단일화 추진에 박차를 가할 것으로 보인다. 비문연대나 바른정당 또는 자유한국당과의 연대가 아니라 독자적인 세력화를 추진할 수 있는 동력을 확보한 것이라는 평가가 지배적이다. 안 전 대표에 대항하고 있는 손 전 대표는 수도권 지역 경선으로 반전을 노리고 있다. 하지만 안 전 대표는 전체 당원의 대다수가 몰려 있는 호남권에서 압도적인 승리를 거뒀다. 앞으로 28일 부산·울산·경남, 30일 대구·경북·강원, 4월 1일 경기, 2일 서울·인천, 4일 대전·충남·충북·세종 경선이 남아있지만 안 전 대표가 호남에서 압도적인 승리를 거두면서 손 전 대표의 역전 가능성은 크게 낮아졌다. 안 전 대표가 호남 뿐 아니라 다른 지역 경선에서까지 압도적인 승리를 거둘 경우 국민의당은 적지 않은 '대선 경쟁력'을 갖출 수 있게 된다. 당 내부적으로는 '이견 없는' 대선 후보를 선출했을 뿐만 아니라 당 외부적으로는 호남 지역 지지도를 바탕으로 문 전 대표에 대항할 수 있는 대항마를 키워냈기 때문이다. 안 전 대표도 이를 인식한 듯 영남 지역 경선을 앞두고 영남 지역을 찾았다. 안 전 대표는 27일 경남 통도사를 찾아 \"부산ㆍ경남에서도 국민의당 경선의 열기를 계속 이어가도록 하겠다. 국민의당이 어떻게 우리나라를 바꾸려고 한다는 비전을 널리 알리는 좋은 계기가 되리라고 본다\"고 말했다. 손 전 대표와 박 부의장 측은 '막판 대역전'을 노리고 있다. 손 전 대표 측은 안 전 대표가 여론조사(20%)에서는 유리할 지 모르지만 현장투표(80%)를 통해 반전을 시도할 수 있을 것으로 보고 있다. 박 부의장 측도 호남향우회 등 지지층을 중심으로 반전을 준비하고 있다.이호승기자 yos547@dt.co.kr디지털타임스 홈페이지 바로가기/SNS 바로가기확바뀐 디지털타임스 연예·스포츠 섹션 바로가기< Copyrights ⓒ 디지털타임스 & dt.co.kr, 무단 전재 및 재배포 금지 >이호승 yos547@"}