{"url": "http://news.naver.com/main/read.nhn?mode=LSD&mid=shm&sid1=100&oid=020&aid=0003055550", "datetime": "2017-04-05 11:49", "contents": "[동아닷컴]사진=JTBC 방송화면안철수 국민의당 대선후보가 손석희 앵커와 인터뷰에서 광주 경선 불법 동원 의혹에 대해 “당에서 위법적인 부분이 있다면 단호하게 대처할 것”이라고 말했다.지난 4일 JTBC ‘뉴스룸’에서 안 후보는 “(경선 결과가)압도적인 승리로 나왔지만 국민의당은 안 전 대표가 만들었고 상대 선수들이 약했던 것이 아닌가”라는 질문에“두 후보 모두 정치적 경력이 많다. 나도 긴장하고 최선을 다했다”고 답했다.이어 손석희 앵커는 \"1대1 구도로 간다고 했는데 단일화 작업 없이도 그대로 갈 것이냐\"고 물었고, 안철수 후보는 \"그게 정도고 순리다\"고 답했다. 손 앵커가 “국민이 만들어주는 연대의 길은 무엇이냐”고 묻자 안 후보는 “국민이 선거로 의사를 표시하실 것이다. 2012년 총선도 더는 양당도 안 된다 생각하고 삼당 체제가 가능하다고 생각하고 신념을 갖고 밀어붙였다. 이번도 마찬가지다”라며 “정권교체는 확실하다. 문재인에 의한 정권교체가 좋은지 안철수에 의한 정권교체가 좋은지만 남았다. 이길 자신 있다”고 말했다.광주 경선 불법 동원 의혹에 대해서는 “당에서 위법적인 부분이 있다면 단호하게 대처할 것”이라고 선을 그었다. “중앙선거관리위원회에서 고발한 상태이기 때문에 사법적인 문제가 생긴다. 그것까지 생각했는가”라는 질문에는 거듭 “불법적 부분이 있으면 나도 단호하게 대처하겠다”고 했다.동아닷컴 디지털뉴스팀 dnews@donga.com▶ 동아일보 단독 / 동아일보 공식 페이스북▶ \"아직도 당신만 모르나 VODA\"ⓒ 동아일보 & donga.com, 무단 전재 및 재배포 금지", "press": "동아일보", "title": "안철수, 손석희의 경선 불법동원 의혹 질문에 “위법적 부분 단호히 대처”"}