{"url": "http://news.naver.com/main/read.nhn?mode=LSD&mid=shm&sid1=100&oid=421&aid=0002662071", "datetime": "2017-04-09 17:06", "contents": "© News1 이은주 디자이너한겨레·한겨레경제사회연구원 의뢰 리서치플러스 조사(서울=뉴스1) 박상휘 기자 = 제19대 대통령선거가 한 달 앞으로 다가온 가운데 문재인 더불어민주당 대선후보와 안철수 국민의당 후보가 지지율에서 백중세를 보였다. 한겨레와 한겨레경제사회연구원이 리서치플러스에 의뢰, 지난 7~8일 전국 성인남녀 1023명을 대상으로 조사해 9일 발표한 여론조사 결과 문 후보와 안 후보는 37.7%로 지지율이 동일한 것으로 집계됐다. 홍준표 자유한국당 후보는 6.6%로 조사됐고 유승민 바른정당 후보 2.1%, 심상정 정의당 후보 2.0%로 나타났다. 김종인 전 의원은 0.4%였다. 지지 후보가 없다는 답변은 6.7%, 모름·무응답은 6.8%다. 홍 후보와 유 후보가 홍 후보로 단일화해 4자 가상 대결이 펼쳐질 경우에는 안 후보(37.4%)가 문 후보(35.8%)를 오차범위 내에서 앞서는 것으로 나타났다. 4자 가상 대결에서 홍 후보는 10.5%였으며 심 후보는 2.6%를 기록했다. 안 후보와 유 후보간 단일화를 해 안 후보가 4자 대결에 나섰을 때는 안 후보가 42.3%, 문 후보는 37.2%로 집계됐다. 이 경우 홍 후보는 7.9%, 심 후보는 2.5%다. 안 후보와 홍 후보, 유 후보가 안 후보로 단일화했을 때의 3자 대결에서는 안 후보 47.4%, 문 후보 38.5%, 심 후보 2.7%로 나타났다.문 후보와 심 후보가 문 후보로 단일화하고, 안 후보, 홍 후보, 유 후보가 안 후보로 단일화했을 경우를 가정한 양자 가상 대결에서도 안 후보(48.2%)가 문 후보(41.8%)를 7.4%포인트 격차로 앞서는 것으로 조사됐다. 이번 조사는 표본오차 95% 신뢰수준에 ±3.1%포인트, 응답률 21.4%이며 자세한 사항은 중앙선거여론조사심의위원회 홈페이지를 참고하면 된다. sanghwi@▶ 놓치면 후회! 최신 만화 보기 / 2017년 나의 운세 보기▶ 여러분의 제보를 기다립니다. 제보하기(클릭!)[© 뉴스1코리아(news1.kr), 무단 전재 및 재배포 금지]", "press": "뉴스1", "title": "문재인-안철수, 6자구도 지지율 37.7% 동률…피말리는 접전"}