{"url": "http://news.naver.com/main/read.nhn?mode=LSD&mid=shm&sid1=100&oid=277&aid=0003969870", "datetime": "2017-04-07 08:05", "contents": "\"安, 박지원 각본에 춤추는 인형에 불과\" 홍준표 자유한국당 대선후보[아시아경제 김보경 기자] 홍준표 자유한국당 대선후보는 7일 \"안철수 국민의당 후보는 지지율이 올라가면 보유주식의 값도 올라가니 좋기는 하겠지만 폭락할 때도 대비하라\"고 경고했다. 홍 후보는 이날 자신의 페이스북을 통해 \"박지원 국민의당 대표가 '홍준표 찍으면 문재인 (당선)된다'고 했다는데 참 어이가 없다\"며 이같이 밝혔다. 그는 \"홍준표 찍으면 홍준표가 되는 것이지 어떻게 해서 문재인이 된다고 하는지 개표과정에서 표 바꿔치기라도 한다는 것인지 참 그렇다\"고 불편한 감정을 드러냈다. 이어 \"오히려 안철수 찍으면 박지원 상왕(上王)된다고 하는 게 맞을 것\"이라며 \"안 후보를 조종하는 분은 박지원씨고 안은 박의 각본에 춤추는 인형에 불과하다\"고 직격탄을 날렸다.  한편 홍 후보는 이날 이회창 전 국무총리 예방, 경기 ·인천 선대위 발대식 등에 참석하며 보수층 결집을 시도한다. 김보경 기자 bkly477@asiae.co.kr▶ 세상의 모든 재미 [티잼]▶ 카드뉴스 ▶ 오늘의 운세<ⓒ세계를 보는 창 경제를 보는 눈, 아시아경제 무단전재 배포금지>", "press": "아시아경제", "title": "홍준표 \"안철수, 주식 폭락할 때도 대비하라\""}