{"url": "http://news.naver.com/main/read.nhn?mode=LSD&mid=shm&sid1=100&oid=448&aid=0000205125", "title": "[속보] 바른정당 대선후보 유승민 \"새로운 보수의 희망 되겠다\"", "press": "TV조선", "datetime": "2017-03-28 17:17", "contents": "바른정당 대선후보, 유승민 확정 [주요발언] 유승민 / 바른정당 대선후보\"바른정당 대선 후보로 용감하게 출발\"\"감동의 대역전 드라마 만들 것\"\"남경필 열정과 투혼 높이 평가\"\"무능한 세력에게 조국 운명 안맡길 것\"\"지금 보수 절체절명의 위기\"\"전직 대통령에 대한 분노 쏟아져\"\"전직 대통령 때문에 보수 매도당해선 안돼\"\"새로운 보수의 희망 되겠다\"\"고통받는 국민 편에서 용감한 개혁할 것\"* 뉴스제보 : 이메일(tvchosun@chosun.com), 카카오톡(tv조선제보), 전화(1661-0190)- Copyrights ⓒ TV조선. 무단전재 및 재배포 금지 -"}