{"url": "http://news.naver.com/main/read.nhn?mode=LSD&mid=shm&sid1=100&oid=421&aid=0002637447", "title": "국민의당 \"유승민 축하…적절한 대통령 탄핵 판단 기억한다\"", "press": "뉴스1", "datetime": "2017-03-28 17:22", "contents": "유승민 바른정당 대선주자가 28일 오후 서울 송파구 올림픽공원 올림픽홀에서 열린 바른정당 제19대 대통령후보자 선출대회에서 정견발표를 하고 있다. 2017.3.28/뉴스1 © News1 박세연 기자바른정당 대통령 후보 유승민 선출에(서울=뉴스1) 박응진 기자 = 국민의당은 28일 \"바른정당 대통령후보로 유승민 의원이 선출된 것을 축하한다\"고 했다. 김경진 수석대변인은 이날 구두논평을 통해 \"박근혜 전 대통령의 탄핵소추 과정에서 바른정당 의원들이 적절한 판단을 했던 과정을 우리는 잘 기억하고 있다\"고 밝혔다. 김 수석대변인은 \"그 정신을 이어받아, 대한민국에 합리적인 법치주의와 다당제가 우리 정치에 정착될 수 있도록 선거과정에서 최선을 다해주길 기대한다\"고 덧붙였다.pej86@▶ 놓치면 후회! 최신 만화 보기 / 2017년 나의 운세 보기▶ 여러분의 제보를 기다립니다. 제보하기(클릭!)[© 뉴스1코리아(news1.kr), 무단 전재 및 재배포 금지]"}