{"url": "http://news.naver.com/main/read.nhn?mode=LSD&mid=shm&sid1=101&oid=029&aid=0002395298", "title": "심상정, \"박 전 대통령 구속...법 앞의 평등 확인한 값진 결정\"", "press": "디지털타임스", "datetime": "2017-03-31 07:37", "contents": "정의당 대선후보인 심상정 대표는 31일 박근혜 전 대통령 구속에 대해 \"법 앞의 평등을 확인한 값진 결정\"이라며 \"박 전 대통령의 구속이 '법의 지배'가 실현되는 '정의로운 대한민국'으로 나아가는 계기가 되기를 바란다\"고 말했다. 그는 \"다시는 이런 불행한 역사가 되풀이 되지 않도록 정의당은 법과 제도개혁에 힘쓰겠다\"고 밝혔다. 심 대표는 이날 입장자료에서 \"박 전 대통령의 구속은 대통령으로서 최소한의 도리도 내팽개치고 형사피의자를 자처한 데 따른 자업자득\"이라며 \"박 전 대통령은 중대한 범죄를 저지르고도 혐의를 조금도 인정하지 않았고 진심 어린 반성과 사과도 없었다\"고 강조했다. 또한 \"전직 대통령 예우를 말하지만, 임기 중 파면된 박 전 대통령은 예우를 받아야 할 '전직 대통령'이 아니다\"라고 덧붙였다.예진수선임기자 jinye@dt.co.kr디지털타임스 홈페이지 바로가기/SNS 바로가기확바뀐 디지털타임스 연예·스포츠 섹션 바로가기< Copyrights ⓒ 디지털타임스 & dt.co.kr, 무단 전재 및 재배포 금지 >예진수 jinye@"}