{"title": "김진태 \"박근혜가 향단이? 그럼 홍준표는 방자\"", "datetime": "2017-03-30 10:16", "contents": "김진태 의원. 사진=뉴시스자유한국당 대선주자 김진태 의원은 30일 '향단이' 발언을 한 홍준표 경남지사를 향해 \"이몽룡인 줄 알았는데 방자였다\"고 비판했다. 김 의원은 이날 YTN라디오 '신율의 출발새아침'에 나와 \"어제 홍 후보가 (박근혜 전 대통령에게) 춘향이인 줄 알았더니 향단이라고 했다\"며 이같이 말했다.김 의원은 홍 지사 측이 '친박 인적청산'을 후보단일화 조건으로 제시했다는 일부 언론 보도에 대해 \"귀를 의심했다. 아마 정당 역사상 처음있는 일 아닐까 싶다\"며 \"치열하게 경합을 하고 있는데 '만약 내가 이기면 다 짐 쌀 각오해, 나는 다른 당 후보와 손잡을 거야'라고 하는게 어디 있느냐\"고 반발했다.유승민 바른정당 대선후보와의 단일화에 대해서는 \"지금부터 단일화하자고 해서 몸집을 높여줄 건 뭐가 있느냐\"며 \"그 당은 완주하기가 힘든 상황이다. 자연스럽게 우리를 도와주는 쪽으로 유도해야 한다\"고 말했다.그는 특히 \"대선 완주가 쉬운 일이 아니다. 선거비용도 수백억원이 들고 지지율 10%를 못 얻으면 환급도 하나도 못 받는다\"며 \"처음부터 단일화가 아니면 안 되는 당이다. 독자적으로 생존이 불가능하다\"고 주장했다.국민의당 대선후보와의 단일화에 대해서도 \"국민의당은 박지원 의원 당인데 저하고는 정말 같이 갈 수 없다\"며 \"이념과 노선이 전혀 다르다\"고 반대했다.정지용 기자 jyjeong@kmib.co.kr[국민일보 홈페이지] [페이스북] [트위터][취재대행소 왱!(클릭)]GoodNews paper ⓒ 국민일보(www.kmib.co.kr), 무단전재 및 재배포금지[뉴스 미란다 원칙] 취재원과 독자에게는 국민일보에 자유로이 접근할 권리와 반론·정정·추후 보도를 청구할 권리가 있습니다. 고충처리인(gochung@kmib.co.kr)/전화:02-781-9711", "url": "http://news.naver.com/main/read.nhn?mode=LSD&mid=shm&sid1=100&oid=005&aid=0000980993", "press": "국민일보"}