{"url": "http://news.naver.com/main/read.nhn?mode=LSD&mid=shm&sid1=100&oid=081&aid=0002811334", "datetime": "2017-04-06 03:37", "contents": "[서울신문]“美 핵전력, 한·미 공동자산으로”바른정당이 5일 김무성·정병국·주호영 공동위원장 체제의 대선 선거대책위를 공식 출범했다. 유승민 후보는 “더불어민주당 문재인 좌파 적폐세력과 민주당의 2중대이자 국가 안보가 불안한 국민의당에 정권이 넘어가지 않게 해야 한다. 도로 친박당인 자유한국당의 자격 없는 후보를 반드시 이길 수 있도록 저와 손을 꼭 잡고 함께해 주시길 간곡히 호소한다”고 밝혔다.유 후보는 “이제부터 고난의 행군을 시작해야 한다. 우리 앞에 자갈 돌밭길, 가시밭길이 있다”면서 “그렇지만 동지 여러분과 함께라면 조금도 두렵지 않다. 어렵고 복잡한 때일수록 국민을 위해 이 나라를 위해 무엇이 원칙이고 명분 있는 길인지만 생각하고 가겠다”고 강조했다. 한국당, 국민의당과의 단일화 가능성이 낮아지고 있는 가운데 끝까지 완주하겠다는 의지를 분명히 밝힌 것이다. 유 후보 측 관계자는 “홍 후보의 행보는 보수를 궤멸시키고 있고 보수 전체를 부끄럽게 하고 있다”면서 “사퇴하는 것이 마땅하다”며 홍 후보와의 단일화에 거리를 뒀다.선거자금 조달의 어려움이 관측되고 있지만 유 후보는 “단 1원도 불법 정치자금을 쓰지 않고 가장 모범적이고 깨끗하게 선거를 치르겠다”면서 “그렇게 하면 국민께서도 우리 바른정당이 정말 바르게 하고 있다는 것을 알아주실 것”이라고 말했다. 한편 유 후보는 이날 미국의 핵 전력의 한·미 공동자산화, 사드급 방어무기 추가 도입 등을 골자로 한 안보공약을 발표했다.허백윤 기자 baikyoon@seoul.co.kr▶  재미있는 세상[나우뉴스], [웰 메이드 N] ▶ [인기 무료만화] [페이스북]ⓒ 서울신문(www.seoul.co.kr), 무단전재 및 재배포금지", "press": "서울신문", "title": "선대위 발족 유승민 “홍준표 보수 궤멸시키고 있다”"}