{"url": "http://news.naver.com/main/read.nhn?mode=LSD&mid=shm&sid1=100&oid=421&aid=0002660320", "datetime": "2017-04-08 08:00", "contents": "홍준표 자유한국당 대선후보가 지난 7일 오후 경기도 안양시 중앙시장을 방문한 후 취재진 질문에 답변하고 있다./뉴스1 © News1 오장환 기자진보·중도 분열 속에 보수 표 모아 당선 전략보수표심, 안철수에 몰리며 고심(서울=뉴스1) 구교운 기자 = 5·9 장미대선을 한달여 앞둔 가운데, 홍준표 자유한국당 대통령후보는 4자 구도에서 보수층 결집을 통해 승리한다는 전략이다.자신이 보수 단일후보로 나서고 문재인 더불어민주당 후보, 안철수 국민의당 후보, 심상정 정의당 후보가 진보와 중도층 표를 두고 3자 경쟁을 벌인다면 승산이 있다는 것이다. 또 다른 보수정당인 유승민 바른정당 후보에 대해서는 '무시전략'을 펴고 있다.홍 후보가 주목하고 있는 것은 노태우 전 대통령이 당선된 1987년 13대 대선이다. 당시 진보진영 주자였던 김영삼·김대중 후보는 단일화를 하지 않았다. 결국 4파전으로 치러진 대선에서 신군부 출신의 노태우 후보가 승리했다.당시 노태우 후보는 36.6%라는 역대 최저 득표율로 당선됐다. 김영삼 통일민주당 후보는 28.0%, 김대중 평화민주당 후보는 27.0%, 김종필 신민주공화당 후보는 8.1%를 얻었다.홍 후보는 각종 여론조사에서 10% 안팎을 기록하고 있다. 드러나지 않고 있는 보수표가 결집할 경우 표가 갈리는 진보진영 주자들을 충분히 제칠 수 있다고 보고 있다.  통상적으로 대한민국의 이념지표에서 보수표를 35% 정도로 분류하고 있다. 중도 진영의 일부 지지세만 가져오면 문·안 후보를 제칠 수 있다는 계산이다.홍 후보는 지난 4일 '보수의 본산(本山)' TK(대구경북)을 시작으로 전국을 돌며 선거대책위원회 발대식 및 필승결의대회를 하고 있다. 박근혜 전 대통령 파면으로 흐트러진 지방 지지세부터 회복해 나가려는 포석이다. 친박(親박근혜) 세력 끌어안기에 공을 들이는가 하면 친박에 비판적인 보수층의 심기를 건드리지 않기 위해서도 노력하고 있다.홍 후보는 지난 4일 대구를 방문해 \"홍준표 정부가 들어서면 박 전 대통령이 산다\"면서도 \"계파 없는 사람이 대통령이 되면 모든 당원·동지들이 같은 형제\"라고 통합을 강조했다.그러나 이같은 전략에도 각종 여론조사에서 안철수 후보 상승세에 올라 문 후보와 양강 구도를 이루고 있는 데 반해 홍 후보는 지지율이 10% 안팎에 머무는 등 정체기를 겪고 있어 고민이 깊다. 보수층이 당선 가능성이 낮은 홍 후보 대신 안 후보를 지지할 가능성이 높다는 분석이 지배적이다.이에 따라 '바다이야기', '노무현 정부는 뇌물 정부' 등 주로 문 후보 공격에 됐던 홍 후보의 공격은 안후보까지 '분산 공략'으로 변경되는 분위기다. 홍 후보 측은 당초 중도로 분류했던 안 후보를 '얼치기 좌파'라고 하거나 '민주당 2중대' '호남 2중대'라고 비판하는 등 안 후보를 영남 유권자들이나 보수층에서 떼어내려고 하고 있다.유창선 정치평론가는 \"보수층은 홍 후보가 당선될 수 있다고 생각하지 않는다\"면서 \"안 후보를 지지하는 것은 전략적 선택\"이라고 말했다. 그러면서 \"보수층 역시 홍 후보의 정치적 자질에 대해 의문을 갖고 있다\"며 \"보수표를 되돌리는 효과는 크지 않을 것\"으로 예측했다.kukoo@▶ 놓치면 후회! 최신 만화 보기 / 2017년 나의 운세 보기▶ 여러분의 제보를 기다립니다. 제보하기(클릭!)[© 뉴스1코리아(news1.kr), 무단 전재 및 재배포 금지]", "press": "뉴스1", "title": "[D-31] 홍준표, 보수층 결집으로 'AGAIN 1987'"}