{"url": "http://news.naver.com/main/read.nhn?mode=LSD&mid=shm&sid1=004&oid=016&aid=0001221804", "datetime": "2017-04-09 23:53", "contents": "[헤럴드경제=이슈섹션] 더불어민주당 문재인 후보의 아들 문준용 씨를 대학에서 가르친 스승, 대학시절 친구의 글이 온라인 상에서 눈길을 끌고 있다. 최근 취업 특혜 의혹 등으로 문 후보에 대한 일부 의혹이 일어나는 것에 대해 정면 반박한 것이다.중앙대에서 사진을 전공한 뒤 중앙대, 건국대 등에서 강사를 했던 사진작가 이흥렬 씨는 6일 자신의 페이스북을 통해 “온몸으로 열심히 연기하는 모습도 대견했지만, 그런 일종의 차별에 대해 자연언어가 아닌 영상언어로 시각화한 것을 보고 뭔가 해낼 친구구나 하고 생각했다”고 밝혔다. 이 씨는 “교수들중 아무도 문군이 문재인씨 아들이란 것을 몰랐다고. 졸업할 때 비로소 알았다고 했다. 그 뒤 2011년인가, 광주 비엔날레에 참가한 주목받는 작가라는 기사에 문준용군이 거론된 것을 우연히 보고 내가 주최한 모임에서 특강을 부탁한 적이 있다”라며 문 씨에 대해 회상했다.그는 또 “정통 사진을 하는 입장에서 관객과 반응하는 인터렉티브 아트는 한마디로 신기하고 훌륭했다. 각광받을 새로운 예술 장르였다. 어찌 보면 정치를 하게 된 아버지로 인해 알게 모르게 조심하며 불이익을 받아 온 문군이다. 차라리 한국을 떠나 편견없는 외국에서 훌륭한 작가로 살아가길 바란다”라고도 적었다.같은날 문 씨의 친구 오민혁 씨의 페이스북 글도 올라왔다. 오 씨는 “(문준용 씨의 스승인) 이흥렬 선생님께서 (소셜미디어에) 작성하신 내용에 지하철 영상 촬영한 친구”라고 자신을 소개했다.오 씨는 “먼저 제가 절친인 걸 아시는 분들이 ‘청와대 들어가겠네~’라는 말씀 많이 하시는데 그런 일 1도 없다”면서 “앞으로도 제가 친구에게 부탁할 수 있는 것은 ‘책에 아버지 사인 좀 받아줘’가 전부다. (저는) 두 아이의 아빠이자 평범한 직장인”이라고 말문을 열었다.또 “한 번은 준용이가 ‘노무현’ 사인이 세겨진 홍주를 가져왔다”면서 “집에서 멋있어 보여서 가져왔다기에 친구네 또 반지하 자취방에서 안주도 없이 마셨다. ‘이거 어디서 났어?’, ‘아버지가 어떻게 청와대 취직하셔서 받으셨어.’ 더 이상 묻지 않았다.(경비하시나 보다..) 당시도 빈곤한 준용이의 생활모습에 아버지가 고위직이라고는 상상도 못하고, 무직이셨는데 ‘경비원으로 취직 하셨나 보다’라고 생각했다”고 적었다.또 그는“준용이는 졸업을 먼저 하고 휴학을 더한 제가 늦게 했는데 어느 날 공무원 준비하던 형이 저에게 먼저 물었다”며 “‘민혁아.. 준용이네 아버지 청와대 계셔? 청와대에 문 씨면 문재인인 거 같은데..’, ‘예전에 뭐 청와대 취직하셨다는 얘기는 들었는데.. 뭐 높은 사람은 아닐걸요’(당시에 민정수석이 누구고 그런 거 잘 몰랐다.) 별 생각 없이 넘겼다”고 회상했다.그러면서 “며칠 뒤 준용이를 만나 맥주 마시는데 생각나서 물었다. ‘준용아, 너네 아버지 성함 ‘문재인’이야?’, ‘어.. 어떻게 알았어?!’, ‘뭘 놀라(당시 생각에 대단한건가..) 추형이 물어봐서..’ 그렇게 친구 아버지의 직업을 알게 되었다”면서 “오래 보다보니 준용이의 부산 초중 친구들도 친하게 되었는데 그 친구들도.. 아버지가 대선 나오실 때 알았다고 하더라”고 전했다.끝으로 “평범한 우리 친구들.. 뭐 하나 하기 힘든.. 준용이한테 힘내라고 밖에 못해 마음이 아프다”고 글을 맺었다.onlinenews@heraldcorp.com▶영감이란 불꽃에 타오르게할 스토리(INSPIRE)▶인기 무료 만화 ▶나만의 변호사 찾기 - Copyrights ⓒ 헤럴드경제 & heraldbiz.com, 무단 전재 및 재배포 금지 -", "press": "헤럴드경제", "title": "문재인 아들 지인들…“청와대 경비원 인줄, 소탈했다”"}