{"url": "http://news.naver.com/main/read.nhn?mode=LSD&mid=shm&sid1=100&oid=014&aid=0003799991", "datetime": "2017-04-07 10:21", "contents": "(홍성=연합뉴스) 배재만 기자 = 더불어민주당 문재인 대선후보가 7일 오전 충남 홍성군 충남도청에서 대선후보 경쟁을 했던 안희정 충남도지사를 만나 악수하고 있다. /연합뉴스    더불어민주당 문재인 대선후보가 7일 경선과정에서 치열하게 싸웠던 안희정 충남지사 껴안기에 나섰다.  경선과정의 앙금을 털고 정권교체의 당위성을 강조하면서 최근 지지율이 상승기류를 타고 있는 국민의당 안철수 후보에 대한 본격적인 견제에 나선 셈이다.  문 후보는 이날 오전 충남도청에서 안 지사와 회동, 지난 경선과정에서 불거진 다양한 갈등을 풀고 화합과 통합의 행보를 토대로 본선에서 힘을 실어줄 것을 당부한 것으로 알려졌다.  문 후보와 안 지사는 또 미세먼지 대책과 충남 민생현안을 해결하기 위한 방안을 논의한 것으로 전해졌다.  문 후보의 대선공약에 안 지사의 대선공약을 비롯해 충남지역 현안 등을 적극 반영시켜 본선 경쟁력을 높이겠다는 취지에서다.  이후 안 지사와 함께 충남 내포 첨단산업단지 조성현장을 방문해 내포 신도시 육성의 구체적인 방안을 논의한다.  이 자리에서 문 후보는 '내포 신도시를 환서해권 중심도시로 육성해 충남 재도약의 거점이 되도록 하겠다'는 청사진을 밝힐 예정이다.  문 후보는 오후에는 충북 일자리 창출의 중심이자 바이오 산업의 현장인 오송 '메타바이오메드'를 방문하고 지역발전 비전을 밝힐 계획이다.   haeneni@fnnews.com 정인홍 기자   ▶ 세상의 모든 골 때리는 이야기 'fn파스'▶ 속보이는 연예뉴스 fn스타  ※ 저작권자 ⓒ  파이낸셜뉴스. 무단 전재-재배포 금지", "press": "파이낸셜뉴스", "title": "[선택 2017]문재인 후보, 경선 앙금털고 '안희정 껴안기' 시도"}