{"url": "http://news.naver.com/main/read.nhn?mode=LSD&mid=shm&sid1=100&oid=014&aid=0003795933", "title": "[선택 2017] 홍준표 “朴 구속영장 청구, 문재인의 대선 전략”", "press": "파이낸셜뉴스", "datetime": "2017-03-30 10:42", "contents": "자유한국당 대선주자인 홍준표 경남도지사는 박근혜 전 대통령의 구속 전 피의자심문(영장실질심사)와 관련해 더불어민주당 문재인 후보의 전략이라고 비판했다.  홍 지사는 30일 페이스북에 올린 글에서 “굳이 파면된 대통령을 또다시 구속하겠다는 검찰의 의도는 문재인 후보의 대선전략에 따른 결정이 아닌가 하는 의심을 지울 수 없다”고 비판했다.  또 홍 지사는 \"우파 대표였던 사람을 짓밟고 가야 대선에서 좌파들을 결집시킬 수 있다고 판단한 것\"이라며 \"한나라를 책임졌던 분으로 의연하고 당당하게 대처해 주길 바란다. 정치투쟁의 장에는 영원한 승자도 영원한 패자도 없다\"고 지적했다. gmin@fnnews.com 조지민 기자   ▶ 세상의 모든 골 때리는 이야기 'fn파스'▶ 속보이는 연예뉴스 fn스타  ※ 저작권자 ⓒ  파이낸셜뉴스. 무단 전재-재배포 금지"}