{"url": "http://news.naver.com/main/read.nhn?mode=LSD&mid=shm&sid1=100&oid=422&aid=0000250436", "datetime": "2017-04-06 21:20", "contents": "[뉴스초점] 문재인, 호남서 통합 행보…안철수, 연대론 일축<출연 : 연합뉴스TV 팽재용 정치부 기자>그럼 오늘의 정치 이슈들을 정치부 팽재용 기자와 함께 정리해보도록 하겠습니다. <질문 1> 먼저 오늘 더불어민주당 문재인 후보의 호남 방문 일정부터 다시 살펴보죠. 오늘이 대선 첫 행보였죠?<질문 2> 이번에는 국민의당 안철수 후보의 발언을 정리해보죠. 아번 선거에서 연대는 없다라는 입장을 밝혔죠?<질문 3> 한편, 오늘 이언주 의원이 민주당을 탈당해 국민의당에 입당했죠? 어떤 배경이 있는 건가요?<질문 4> 이번에는 보수 진영 후보들을 살펴보죠. 한국당 홍준표 후보는 호남을 방문했고 바른정당 유승민 후보는 PK 지역을 공략했죠?연합뉴스TV : 02-398-4441(기사문의) 4409(제보), 카톡/라인 jebo23 ▶ 연합뉴스TV 생방송 시청 | 뉴스스탠드 구독 ▶ 대한민국 뉴스의 시작, 연합뉴스TV 앱 다운받기", "press": "연합뉴스TV", "title": "[뉴스초점] 문재인, 호남서 통합 행보…안철수, 연대론 일축"}