{"url": "http://news.naver.com/main/read.nhn?mode=LSD&mid=shm&sid1=100&oid=018&aid=0003789484", "datetime": "2017-04-03 20:28", "contents": "더불어민주당 제19대 대통령후보자 수도권·강원·제주 선출대회가 3일 오후 서울 구로구 고척스카이돔에서 열린 가운데 문재인 후보가 정견발표를 하고 있다.(사진-노진환 기자)[이데일리 김영환 기자] 더불어민주당 대선 후보로 문재인 후보가 결정되면서 ‘문재인 대세론’이 당내 경선을 넘어 본선에서도 유지될지에 관심이 쏠린다. 사실상 보수 진영이 힘을 못 쓰고 있는 상황에서 문 후보의 대항마로 안철수 국민의당 대선 경선 후보가 꼽히고 있기 때문이다.문 후보는 3일 서울 고척돔에서 종료된 민주당 경선에서 누적 득표율 57.0%로 압승하며 대선 후보로 선출됐다. 이제 문 후보가 증명해야 할 것은 정당 내 지지율이 아닌 전국적인 지지다. 리얼미터 기준 13주 연속 1위를 달리고 있는 만큼 경선 이후 당내 비문 진영 감싸안기가 우선 과제가 될 전망이다. 민주당을 향하는 지지율이 과반을 넘고 있어 이들만 잘 추스려도 본선 경쟁력을 갖출 수 있다.특히 경쟁을 벌였던 안희정 후보와 이재명 후보가 스펙트럼이 전혀 다르다는 점에서 문 후보에게는 이탈되는 지지층을 최소화하는 것이 필요하다. 안 후보는 상대적으로 중도 보수층을 지지층으로 두고 있고 이 후보는 진보층으로부터 지지를 받고 있다. 두 후보가 넓힌 민주당의 외연을 문 후보가 흡수할 수 있을지에 관심이 쏠린다. 문 후보로서는 지지층을 모두 아우를 수 있는 묘수가 필요한 상황이다.그러나 분위기는 녹록치 않다. 경선을 치르면서 쌓인 후보들간 앙금이 남아있다. 이날 경선을 치렀던 고척돔 앞에는 이 후보의 지지자들이 ‘ARS 투표 데이터를 보존하라’면서 선거 과정에 대한 의혹을 제기했다. 지난 2일에도 이 후보 측 관계자가 재외국민 투표에 대한 의문을 공개적으로 밝혔다. 문 후보가 영입 인사를 통해 ‘개혁적 보수’ 끌어안기를 계속하면서 진보적 성향의 이 후보 지지자들이 문 후보로 향하는 데 장벽이 되고 있다.안 후보 측 사정도 비슷하다. 안 후보는 “질린다”는 표현을 직접적으로 했을 만큼, 문 후보에 대한 반감을 드러냈다. 특히 안 후보가 안철수 국민의당 대선 경선 후보에게 쏠리는 중도 보수의 표심을 확보해뒀다는 점에서 안 후보 지지자들을 달랠 처방이 필요하다. 실제로 안 후보를 지지하는 지지층이 안 후보가 경선에서 밀려날 경우 안철수 후보로 상당 부분 이동할 것이라는 여론조사가 있어왔다. 문 후보로서는 안 후보를 향한 표심이, 맞대결이 예상되는 안철수 후보에게 옮아가는 것은 부담스럽다. 외곽 진영의 연대도 문재인 대세론에 영향을 미칠 변수다. 국민의당과 바른정당이 손을 맞잡게 될 경우 미칠 시너지는 예상하기 어렵다. 이렇다할 대항마가 없어 투표를 포기하거나 마지못해 문 후보를 지지하는 지지자들이 중도 보수층의 표심이 결집하는 양상이 보이면 변심을 할 수 있기 때문이다.일단 초미의 관심사는 민주당 경선 이후 대선 후보군에서 안희정·이재명 보기가 빠진 뒤의 지지율 여론조사다. 문 후보로서는 40%가 넘는 지지율을 확보하면서 대세론을 이어가야 하고, 다른 정당 후보들은 안희정·이재명 후보의 표를 흡수해야 한다. 지난 2007년 대선에서 대세론을 이뤘던 이명박 전 대통령은 박근혜 당시 후보와의 경선에서 승리한 이후 50%대의 높은 지지율을 확보한 바 있다.김영환 (kyh1030@edaily.co.kr)＜ⓒ종합 경제정보 미디어 이데일리 - 무단전재 & 재배포 금지＞", "press": "이데일리", "title": "문재인 대세론, 막판까지 이어질까"}